constants/__init__.py
constants/fields.py
constants/models.py
constants/nlp.py
constants/paths.py
constants/regex.py
constants/replacements.py
crawlers/__init__.py
crawlers/arxiv_crawler.py
crawlers/biorxiv_crawler.py
crawlers/doij_crawler.py
crawlers/egu_crawler.py
crawlers/hal_crawler.py
crawlers/iahr_crawler.py
crawlers/issn_crawler.py
crawlers/iwa_crawler.py
crawlers/pubmed_crawler.py
crawlers/scholar_crawler.py
crawlers/ssrn_crawler.py
data_constructors/__init__.py
data_constructors/omr_classif_data.py
data_queriers/__init__.py
data_queriers/base.py
data_queriers/custom_querier.py
data_queriers/sqlite_manager.py
data_queriers/with_keywords.py
data_queriers/with_semantics.py
models/__init__.py
models/abbreviation.py
models/papers_classification/__init__.py
models/papers_classification/obj_classifier.py
models/papers_classification/omr_review_classifier.py
models/papers_classification/semantic_search.py
models/papers_classification/tfidf.py
models/papers_classification/bomr_classif/__init__.py
models/papers_classification/bomr_classif/ner_classifier.py
models/papers_classification/bomr_classif/ner_processor.py
models/papers_classification/bomr_classif/omr_segmentors.py
models/papers_classification/bomr_classif/trainer.py
models/text_generation/__init__.py
models/text_generation/clauses_processing.py
models/text_generation/direct2reported.py
models/text_generation/paper2reported.py
models/text_generation/query2review.py
models/text_generation/query_generation.py
naimai/__init__.py
naimai/decorators.py
naimai/gcloud.py
naimai/processing.py
naimai/constants/__init__.py
naimai/constants/fields.py
naimai/constants/models.py
naimai/constants/nlp.py
naimai/constants/paths.py
naimai/constants/regex.py
naimai/constants/replacements.py
naimai/crawlers/__init__.py
naimai/crawlers/arxiv_crawler.py
naimai/crawlers/biorxiv_crawler.py
naimai/crawlers/doij_crawler.py
naimai/crawlers/egu_crawler.py
naimai/crawlers/hal_crawler.py
naimai/crawlers/iahr_crawler.py
naimai-1.0.0.6.dist-info/LICENSE
naimai-1.0.0.6.dist-info/METADATA
naimai-1.0.0.6.dist-info/WHEEL
naimai-1.0.0.6.dist-info/top_level.txt
naimai-1.0.0.6.dist-info/RECORD
