Metadata-Version: 2.1
Name: naimai
Version: 1.0.0.6
Summary: Python library to help with scientific literature research
Home-page: https://github.com/yassinekdi/naimai
Author: Yassine Kaddi
Author-email: yassine@naimai.fr
Maintainer: Yassine Kaddi
Maintainer-email: yassine@naimai.fr
License: CC BY-NC-SA
Keywords: science,review,bibliography,python,nlp,machine-learning,information-extraction
Platform: UNKNOWN
Classifier: Programming Language :: Python :: 3.6
Classifier: Programming Language :: Python :: 3.7
Classifier: Programming Language :: Python :: 3.8
Classifier: Operating System :: OS Independent
Requires-Dist: Unidecode (==1.3.6)
Requires-Dist: beautifulsoup4 (==4.11.1)
Requires-Dist: datasets (==2.6.1)
Requires-Dist: habanero (==1.2.2)
Requires-Dist: keybert (==0.7.0)
Requires-Dist: lxml (==4.9.1)
Requires-Dist: matplotlib (==3.2.2)
Requires-Dist: numpy (==1.21.6)
Requires-Dist: pandas (==1.3.2)
Requires-Dist: pyinflect (==0.5.1)
Requires-Dist: requests (==2.23.0)
Requires-Dist: scikit-learn (==1.0.2)
Requires-Dist: sentence-transformers (==2.2.2)
Requires-Dist: seqeval (==1.2.2)
Requires-Dist: spacy (==3.4.2)
Requires-Dist: spacy-langdetect (==0.1.2)
Requires-Dist: torch (==1.13.0)
Requires-Dist: tqdm (==4.64.1)
